chatcsvai/__init__.py
chatcsvai/cli.py
chatcsvai/core.py
chatcsvai-0.2.2.dist-info/METADATA
chatcsvai-0.2.2.dist-info/WHEEL
chatcsvai-0.2.2.dist-info/entry_points.txt
chatcsvai-0.2.2.dist-info/top_level.txt
chatcsvai-0.2.2.dist-info/RECORD
