Metadata-Version: 2.4
Name: chatcsvai
Version: 0.2.2
Summary: A chatbot for interacting with CSV files using AI.
Author-email: Lucky Kandpal <luckykandpal091@gmail.com>
Requires-Python: >=3.8
Requires-Dist: pandas<3.0.0,>=1.3.0
Requires-Dist: duckdb>=0.3.2
Requires-Dist: sentence-transformers<5.0.0,>=2.2.0
Requires-Dist: langchain<0.4.0,>=0.1.0
Requires-Dist: langchain-core<0.4.0,>=0.0.1
Requires-Dist: langchain-community<0.4.0,>=0.0.1
Requires-Dist: langchain-huggingface<0.3.0,>=0.0.1
Requires-Dist: langchain-groq<0.4.0,>=0.0.1
Requires-Dist: langchain-experimental<0.4.0,>=0.0.1
Requires-Dist: python-dotenv>=1.0.0
